{"Order":{"ID":"a9a00df6-5591-4b8a-b6da-4c88512b069b","Table":{"Number":6,"Seats":2,"IsOccupied":true},"Products":[{"Name":"Mojito","Price":9,"Type":"Drink"}],"TotalAmount":9,"OrderTime":"2024-08-08T21:20:20.9772195+03:00"},"Id":"8bb7ab78-9f15-4e87-9229-ad76767d1b19","Type":"Restaurant"}
{"Order":{"ID":"35c16f75-9417-4055-a51d-188f056c7112","Table":{"Number":3,"Seats":2,"IsOccupied":true},"Products":[{"Name":"Saltibarsciai","Price":6,"Type":"Food"},{"Name":"Aperol Spritz","Price":12,"Type":"Drink"}],"TotalAmount":18,"OrderTime":"2024-08-08T21:10:40.0995266+03:00"},"Id":"1adc2c20-bd15-4378-9ca1-d609bb7ea6d5","Type":"Restaurant"}
{"Order":{"ID":"6ed22f46-7350-4a22-946a-6f9a4292a9e5","Table":{"Number":5,"Seats":4,"IsOccupied":true},"Products":[{"Name":"Aperol Spritz","Price":12,"Type":"Drink"}],"TotalAmount":12,"OrderTime":"2024-08-08T19:10:47.8964248+03:00"},"Id":"54a2c08b-13b3-41c7-81b7-bfbe07b179a8","Type":"Restaurant"}
{"Order":{"ID":"8a12e8a3-4c21-4e3d-81aa-b2579c8b9e77","Table":{"Number":1,"Seats":2,"IsOccupied":true},"Products":[{"Name":"Mojito","Price":9,"Type":"Drink"}],"TotalAmount":9,"OrderTime":"2024-08-08T20:57:09.8864364+03:00"},"Id":"c2e14c41-35dd-44a8-a366-3923bb68e2db","Type":"Restaurant"}
{"Order":{"ID":"22f4c168-ae72-48be-a31e-950c70831d9a","Table":{"Number":5,"Seats":4,"IsOccupied":true},"Products":[{"Name":"Medaus pyragas","Price":6,"Type":"Food"}],"TotalAmount":6,"OrderTime":"2024-08-08T21:34:18.9878781+03:00"},"Id":"23c8b174-357c-4e88-bf7b-5a81c71bde0b","Type":"Restaurant"}
